Workbook

Sheet Instructions
A1: ClassUp QA Test Plan
A2: End-to-end test cases covering every feature of ClassUp v2
A4: How to use this sheet
A5: 1. | B5: Go to the 'Test Cases' tab.
A6: 2. | B6: Work through each row in order (tests are grouped by module).
A7: 3. | B7: Follow the 'Pre-conditions' and 'Test Steps' columns.
A8: 4. | B8: Compare the app's behaviour with the 'Expected Outcome' column.
A9: 5. | B9: Set 'Status' to Pass, Fail, Blocked, or Not Run using the dropdown.
A10: 6. | B10: Fill in 'Actual Result' with what you observed (important for failures).
A11: 7. | B11: Add any bug details or screenshot references in 'Notes / Bugs'.
A12: 8. | B12: The 'Summary' tab auto-calculates pass rates per module.
A14: Priorities
A15: Critical | B15: Must work before any launch. Blocks everything.
A16: High | B16: Core feature, must work in first release.
A17: Medium | B17: Important but not blocking.
A18: Low | B18: Nice-to-have / edge case.
A20: Test types
A21: Smoke | B21: Core happy path — must always pass.
A22: Functional | B22: Feature works as described.
A23: Negative | B23: Invalid input is handled gracefully.
A24: Security | B24: Permissions, injection, isolation.
A25: Permission | B25: Role-based access control.
A26: Regression | B26: Previously-found bug should not return.
A27: UI | B27: Look, layout, responsive, copy.
A29: Test accounts (ask dev team)
A30: Super Admin | B30: russel@rfm.org.za
A31: School Admin | B31: admin@sunshinedaycare.co.za
A32: Teacher | B32: (provided separately)
A33: Parent | B33: (provided separately)
A35: Tester | B35: (Name)
A36: Test environment | B36: (URL)
A37: Test run date | B37: (YYYY-MM-DD)
A38: Build / commit | B38: (git SHA)

Sheet Test Cases
A1: Test ID | B1: Module | C1: Feature | D1: Test Case Description | E1: Pre-conditions | F1: Test Steps | G1: Expected Outcome | H1: Priority | I1: Type | J1: Status | K1: Actual Result | L1: Notes / Bugs
A2: AUTH-001 | B2: Authentication | C2: Login (happy path) | D2: Admin can log in with valid credentials | E2: School admin account exists | F2: 1. Go to /login 2. Enter valid email + password 3. Click 'Log In' | G2: Redirected to /dashboard with welcome message. Session cookie set. | H2: Critical | I2: Smoke | J2: Not Run
A3: AUTH-002 | B3: Authentication | C3: Login (wrong password) | D3: Invalid password rejected | E3: School admin account exists | F3: 1. Go to /login 2. Enter valid email + wrong password 3. Click 'Log In' | G3: Error message shown. Still on /login. No session cookie. | H3: Critical | I3: Negative | J3: Not Run
A4: AUTH-003 | B4: Authentication | C4: Login (non-existent email) | D4: Unknown email rejected | E4: None | F4: 1. Go to /login 2. Enter unregistered email 3. Click 'Log In' | G4: Generic auth error (must NOT reveal whether email exists). | H4: High | I4: Security | J4: Not Run
A5: AUTH-004 | B5: Authentication | C5: Rate limiting | D5: Login brute force is rate limited | E5: None | F5: 1. Attempt login with wrong password 11+ times in 1 minute | G5: After ~10 attempts, receive 429 Too Many Requests error. | H5: High | I5: Security | J5: Not Run
A6: AUTH-005 | B6: Authentication | C6: Forgot password | D6: User can request password reset email | E6: User account exists | F6: 1. Click 'Forgot Password?' on login 2. Enter email 3. Submit | G6: Success message shown. Reset email delivered within 1 minute. | H6: High | I6: Functional | J6: Not Run
A7: AUTH-006 | B7: Authentication | C7: Reset password | D7: User can reset password with valid token | E7: Password reset email received | F7: 1. Click reset link in email 2. Enter new password (min 8 chars) 3. Submit | G7: Password updated. User can log in with new password. | H7: High | I7: Functional | J7: Not Run
A8: AUTH-007 | B8: Authentication | C8: Reset password (expired) | D8: Expired reset token rejected | E8: Reset email received more than 24h ago | F8: 1. Click reset link 2. Submit new password | G8: Error: token expired or invalid. Password unchanged. | H8: Medium | I8: Negative | J8: Not Run
A9: AUTH-008 | B9: Authentication | C9: Logout | D9: User can log out | E9: Logged in | F9: 1. Click profile menu 2. Click 'Log Out' | G9: Redirected to /login. Session cookie cleared. Cannot access /dashboard. | H9: Critical | I9: Smoke | J9: Not Run
A10: AUTH-009 | B10: Authentication | C10: Profile update | D10: User updates own profile | E10: Logged in | F10: 1. Go to /profile 2. Update first name / phone / language 3. Save | G10: Success toast. Changes persisted after reload. | H10: Medium | I10: Functional | J10: Not Run
A11: AUTH-010 | B11: Authentication | C11: Change password | D11: User changes own password | E11: Logged in | F11: 1. Go to /profile 2. Enter current + new password 3. Submit | G11: Success toast. Log out and log in with new password succeeds. | H11: High | I11: Functional | J11: Not Run
A12: ONB-001 | B12: Onboarding | C12: Wizard triggers on first login | D12: New school admin sees 5-step onboarding wizard | E12: New tenant created, first admin login | F12: 1. Log in for the first time | G12: Redirected to /onboarding step 1. | H12: Critical | I12: Smoke | J12: Not Run
A13: ONB-002 | B13: Onboarding | C13: Step 1: School info | D13: Admin fills in school details | E13: On onboarding step 1 | F13: 1. Enter school name, address, timezone 2. Upload logo 3. Pick colors 4. Next | G13: Progress saved. Advances to step 2. | H13: High | I13: Functional | J13: Not Run
... A139: UI-005 | B139: UI/UX | C139: Error page | D139: Friendly 404 page | E139: None | F139: 1. Visit /nonexistent-page | G139: Custom 404 page with link back to dashboard. | H139: Medium | I139: UI | J139: Not Run

Sheet Summary
A1: Test Run Summary
A3: Overall
A4: Total | B4: Pass | C4: Fail | D4: Blocked | E4: Not Run | F4: Pass %
A5: =COUNTA('Test Cases'!A2:A139) | B5: =COUNTIF('Test Cases'!J2:J139,"Pass") | C5: =COUNTIF('Test Cases'!J2:J139,"Fail") | D5: =COUNTIF('Test Cases'!J2:J139,"Blocked") | E5: =COUNTIF('Test Cases'!J2:J139,"Not Run") | F5: =IF(A5=0,0,B5/A5)
A7: Per-Module Breakdown
A8: Module | B8: Total | C8: Pass | D8: Fail | E8: Blocked | F8: Not Run | G8: Pass %
A9: Authentication | B9: =COUNTIF('Test Cases'!B2:B139,"Authentication") | C9: =COUNTIFS('Test Cases'!B2:B139,"Authentication",'Test Cases'!J2:J139,"Pass") | D9: =COUNTIFS('Test Cases'!B2:B139,"Authentication",'Test Cases'!J2:J139,"Fail") | E9: =COUNTIFS('Test Cases'!B2:B139,"Authentication",'Test Cases'!J2:J139,"Blocked") | F9: =COUNTIFS('Test Cases'!B2:B139,"Authentication",'Test Cases'!J2:J139,"Not Run") | G9: =IF(B9=0,0,C9/B9)
A10: Onboarding | B10: =COUNTIF('Test Cases'!B2:B139,"Onboarding") | C10: =COUNTIFS('Test Cases'!B2:B139,"Onboarding",'Test Cases'!J2:J139,"Pass") | D10: =COUNTIFS('Test Cases'!B2:B139,"Onboarding",'Test Cases'!J2:J139,"Fail") | E10: =COUNTIFS('Test Cases'!B2:B139,"Onboarding",'Test Cases'!J2:J139,"Blocked") | F10: =COUNTIFS('Test Cases'!B2:B139,"Onboarding",'Test Cases'!J2:J139,"Not Run") | G10: =IF(B10=0,0,C10/B10)
A11: Students | B11: =COUNTIF('Test Cases'!B2:B139,"Students") | C11: =COUNTIFS('Test Cases'!B2:B139,"Students",'Test Cases'!J2:J139,"Pass") | D11: =COUNTIFS('Test Cases'!B2:B139,"Students",'Test Cases'!J2:J139,"Fail") | E11: =COUNTIFS('Test Cases'!B2:B139,"Students",'Test Cases'!J2:J139,"Blocked") | F11: =COUNTIFS('Test Cases'!B2:B139,"Students",'Test Cases'!J2:J139,"Not Run") | G11: =IF(B11=0,0,C11/B11)
A12: Classes | B12: =COUNTIF('Test Cases'!B2:B139,"Classes") | C12: =COUNTIFS('Test Cases'!B2:B139,"Classes",'Test Cases'!J2:J139,"Pass") | D12: =COUNTIFS('Test Cases'!B2:B139,"Classes",'Test Cases'!J2:J139,"Fail") | E12: =COUNTIFS('Test Cases'!B2:B139,"Classes",'Test Cases'!J2:J139,"Blocked") | F12: =COUNTIFS('Test Cases'!B2:B139,"Classes",'Test Cases'!J2:J139,"Not Run") | G12: =IF(B12=0,0,C12/B12)
A13: Teachers | B13: =COUNTIF('Test Cases'!B2:B139,"Teachers") | C13: =COUNTIFS('Test Cases'!B2:B139,"Teachers",'Test Cases'!J2:J139,"Pass") | D13: =COUNTIFS('Test Cases'!B2:B139,"Teachers",'Test Cases'!J2:J139,"Fail") | E13: =COUNTIFS('Test Cases'!B2:B139,"Teachers",'Test Cases'!J2:J139,"Blocked") | F13: =COUNTIFS('Test Cases'!B2:B139,"Teachers",'Test Cases'!J2:J139,"Not Run") | G13: =IF(B13=0,0,C13/B13)
A14: Parents | B14: =COUNTIF('Test Cases'!B2:B139,"Parents") | C14: =COUNTIFS('Test Cases'!B2:B139,"Parents",'Test Cases'!J2:J139,"Pass") | D14: =COUNTIFS('Test Cases'!B2:B139,"Parents",'Test Cases'!J2:J139,"Fail") | E14: =COUNTIFS('Test Cases'!B2:B139,"Parents",'Test Cases'!J2:J139,"Blocked") | F14: =COUNTIFS('Test Cases'!B2:B139,"Parents",'Test Cases'!J2:J139,"Not Run") | G14: =IF(B14=0,0,C14/B14)
A15: Attendance | B15: =COUNTIF('Test Cases'!B2:B139,"Attendance") | C15: =COUNTIFS('Test Cases'!B2:B139,"Attendance",'Test Cases'!J2:J139,"Pass") | D15: =COUNTIFS('Test Cases'!B2:B139,"Attendance",'Test Cases'!J2:J139,"Fail") | E15: =COUNTIFS('Test Cases'!B2:B139,"Attendance",'Test Cases'!J2:J139,"Blocked") | F15: =COUNTIFS('Test Cases'!B2:B139,"Attendance",'Test Cases'!J2:J139,"Not Run") | G15: =IF(B15=0,0,C15/B15)
A16: Messaging | B16: =COUNTIF('Test Cases'!B2:B139,"Messaging") | C16: =COUNTIFS('Test Cases'!B2:B139,"Messaging",'Test Cases'!J2:J139,"Pass") | D16: =COUNTIFS('Test Cases'!B2:B139,"Messaging",'Test Cases'!J2:J139,"Fail") | E16: =COUNTIFS('Test Cases'!B2:B139,"Messaging",'Test Cases'!J2:J139,"Blocked") | F16: =COUNTIFS('Test Cases'!B2:B139,"Messaging",'Test Cases'!J2:J139,"Not Run") | G16: =IF(B16=0,0,C16/B16)
A17: Files | B17: =COUNTIF('Test Cases'!B2:B139,"Files") | C17: =COUNTIFS('Test Cases'!B2:B139,"Files",'Test Cases'!J2:J139,"Pass") | D17: =COUNTIFS('Test Cases'!B2:B139,"Files",'Test Cases'!J2:J139,"Fail") | E17: =COUNTIFS('Test Cases'!B2:B139,"Files",'Test Cases'!J2:J139,"Blocked") | F17: =COUNTIFS('Test Cases'!B2:B139,"Files",'Test Cases'!J2:J139,"Not Run") | G17: =IF(B17=0,0,C17/B17)
A18: Reports | B18: =COUNTIF('Test Cases'!B2:B139,"Reports") | C18: =COUNTIFS('Test Cases'!B2:B139,"Reports",'Test Cases'!J2:J139,"Pass") | D18: =COUNTIFS('Test Cases'!B2:B139,"Reports",'Test Cases'!J2:J139,"Fail") | E18: =COUNTIFS('Test Cases'!B2:B139,"Reports",'Test Cases'!J2:J139,"Blocked") | F18: =COUNTIFS('Test Cases'!B2:B139,"Reports",'Test Cases'!J2:J139,"Not Run") | G18: =IF(B18=0,0,C18/B18)
A19: Academic | B19: =COUNTIF('Test Cases'!B2:B139,"Academic") | C19: =COUNTIFS('Test Cases'!B2:B139,"Academic",'Test Cases'!J2:J139,"Pass") | D19: =COUNTIFS('Test Cases'!B2:B139,"Academic",'Test Cases'!J2:J139,"Fail") | E19: =COUNTIFS('Test Cases'!B2:B139,"Academic",'Test Cases'!J2:J139,"Blocked") | F19: =COUNTIFS('Test Cases'!B2:B139,"Academic",'Test Cases'!J2:J139,"Not Run") | G19: =IF(B19=0,0,C19/B19)
A20: Timetable | B20: =COUNTIF('Test Cases'!B2:B139,"Timetable") | C20: =COUNTIFS('Test Cases'!B2:B139,"Timetable",'Test Cases'!J2:J139,"Pass") | D20: =COUNTIFS('Test Cases'!B2:B139,"Timetable",'Test Cases'!J2:J139,"Fail") | E20: =COUNTIFS('Test Cases'!B2:B139,"Timetable",'Test Cases'!J2:J139,"Blocked") | F20: =COUNTIFS('Test Cases'!B2:B139,"Timetable",'Test Cases'!J2:J139,"Not Run") | G20: =IF(B20=0,0,C20/B20)
A21: Billing | B21: =COUNTIF('Test Cases'!B2:B139,"Billing") | C21: =COUNTIFS('Test Cases'!B2:B139,"Billing",'Test Cases'!J2:J139,"Pass") | D21: =COUNTIFS('Test Cases'!B2:B139,"Billing",'Test Cases'!J2:J139,"Fail") | E21: =COUNTIFS('Test Cases'!B2:B139,"Billing",'Test Cases'!J2:J139,"Blocked") | F21: =COUNTIFS('Test Cases'!B2:B139,"Billing",'Test Cases'!J2:J139,"Not Run") | G21: =IF(B21=0,0,C21/B21)
A22: Subscriptions | B22: =COUNTIF('Test Cases'!B2:B139,"Subscriptions") | C22: =COUNTIFS('Test Cases'!B2:B139,"Subscriptions",'Test Cases'!J2:J139,"Pass") | D22: =COUNTIFS('Test Cases'!B2:B139,"Subscriptions",'Test Cases'!J2:J139,"Fail") | E22: =COUNTIFS('Test Cases'!B2:B139,"Subscriptions",'Test Cases'!J2:J139,"Blocked") | F22: =COUNTIFS('Test Cases'!B2:B139,"Subscriptions",'Test Cases'!J2:J139,"Not Run") | G22: =IF(B22=0,0,C22/B22)
A23: Settings | B23: =COUNTIF('Test Cases'!B2:B139,"Settings") | C23: =COUNTIFS('Test Cases'!B2:B139,"Settings",'Test Cases'!J2:J139,"Pass") | D23: =COUNTIFS('Test Cases'!B2:B139,"Settings",'Test Cases'!J2:J139,"Fail") | E23: =COUNTIFS('Test Cases'!B2:B139,"Settings",'Test Cases'!J2:J139,"Blocked") | F23: =COUNTIFS('Test Cases'!B2:B139,"Settings",'Test Cases'!J2:J139,"Not Run") | G23: =IF(B23=0,0,C23/B23)
A24: Security | B24: =COUNTIF('Test Cases'!B2:B139,"Security") | C24: =COUNTIFS('Test Cases'!B2:B139,"Security",'Test Cases'!J2:J139,"Pass") | D24: =COUNTIFS('Test Cases'!B2:B139,"Security",'Test Cases'!J2:J139,"Fail") | E24: =COUNTIFS('Test Cases'!B2:B139,"Security",'Test Cases'!J2:J139,"Blocked") | F24: =COUNTIFS('Test Cases'!B2:B139,"Security",'Test Cases'!J2:J139,"Not Run") | G24: =IF(B24=0,0,C24/B24)
A25: UI/UX | B25: =COUNTIF('Test Cases'!B2:B139,"UI/UX") | C25: =COUNTIFS('Test Cases'!B2:B139,"UI/UX",'Test Cases'!J2:J139,"Pass") | D25: =COUNTIFS('Test Cases'!B2:B139,"UI/UX",'Test Cases'!J2:J139,"Fail") | E25: =COUNTIFS('Test Cases'!B2:B139,"UI/UX",'Test Cases'!J2:J139,"Blocked") | F25: =COUNTIFS('Test Cases'!B2:B139,"UI/UX",'Test Cases'!J2:J139,"Not Run") | G25: =IF(B25=0,0,C25/B25)
A28: By Priority
A29: Priority | B29: Total | C29: Pass | D29: Fail | E29: Pass %
A30: Critical | B30: =COUNTIF('Test Cases'!H2:H139,"Critical") | C30: =COUNTIFS('Test Cases'!H2:H139,"Critical",'Test Cases'!J2:J139,"Pass") | D30: =COUNTIFS('Test Cases'!H2:H139,"Critical",'Test Cases'!J2:J139,"Fail") | E30: =IF(B30=0,0,C30/B30)
A31: High | B31: =COUNTIF('Test Cases'!H2:H139,"High") | C31: =COUNTIFS('Test Cases'!H2:H139,"High",'Test Cases'!J2:J139,"Pass") | D31: =COUNTIFS('Test Cases'!H2:H139,"High",'Test Cases'!J2:J139,"Fail") | E31: =IF(B31=0,0,C31/B31)
A32: Medium | B32: =COUNTIF('Test Cases'!H2:H139,"Medium") | C32: =COUNTIFS('Test Cases'!H2:H139,"Medium",'Test Cases'!J2:J139,"Pass") | D32: =COUNTIFS('Test Cases'!H2:H139,"Medium",'Test Cases'!J2:J139,"Fail") | E32: =IF(B32=0,0,C32/B32)
A33: Low | B33: =COUNTIF('Test Cases'!H2:H139,"Low") | C33: =COUNTIFS('Test Cases'!H2:H139,"Low",'Test Cases'!J2:J139,"Pass") | D33: =COUNTIFS('Test Cases'!H2:H139,"Low",'Test Cases'!J2:J139,"Fail") | E33: =IF(B33=0,0,C33/B33)
